skillshare_dl/__init__.py
skillshare_dl/cli.py
skillshare_dl/main.py
skillshare_dl-0.0.3.dist-info/METADATA
skillshare_dl-0.0.3.dist-info/WHEEL
skillshare_dl-0.0.3.dist-info/entry_points.txt
skillshare_dl-0.0.3.dist-info/licenses/LICENSE
skillshare_dl-0.0.3.dist-info/RECORD
